pyamino
